pulumi_danubedata/__init__.py
pulumi_danubedata/_inputs.py
pulumi_danubedata/_utilities.py
pulumi_danubedata/cache.py
pulumi_danubedata/database.py
pulumi_danubedata/firewall.py
pulumi_danubedata/get_cache_providers.py
pulumi_danubedata/get_caches.py
pulumi_danubedata/get_database_providers.py
pulumi_danubedata/get_databases.py
pulumi_danubedata/get_firewalls.py
pulumi_danubedata/get_serverless_containers.py
pulumi_danubedata/get_ssh_keys.py
pulumi_danubedata/get_storage_access_keys.py
pulumi_danubedata/get_storage_buckets.py
pulumi_danubedata/get_vps_images.py
pulumi_danubedata/get_vps_snapshots.py
pulumi_danubedata/get_vpss.py
pulumi_danubedata/outputs.py
pulumi_danubedata/provider.py
pulumi_danubedata/pulumi-plugin.json
pulumi_danubedata/py.typed
pulumi_danubedata/serverless.py
pulumi_danubedata/ssh_key.py
pulumi_danubedata/storage_access_key.py
pulumi_danubedata/storage_bucket.py
pulumi_danubedata/vps.py
pulumi_danubedata/vps_snapshot.py
pulumi_danubedata/config/__init__.py
pulumi_danubedata/config/__init__.pyi
pulumi_danubedata/config/vars.py
pulumi_danubedata-0.1.7.dist-info/METADATA
pulumi_danubedata-0.1.7.dist-info/WHEEL
pulumi_danubedata-0.1.7.dist-info/top_level.txt
pulumi_danubedata-0.1.7.dist-info/RECORD
