Metadata-Version: 2.4
Name: pulumi_danubedata
Version: 0.1.7
Summary: A Pulumi provider for managing DanubeData cloud infrastructure resources.
Home-page: https://danubedata.ro
License: Apache-2.0
Project-URL: Repository, https://github.com/AdrianSilaghi/pulumi-danubedata
Keywords: pulumi danubedata category/cloud kind/native
Requires-Python: >=3.8
Requires-Dist: parver>=0.2.1
Requires-Dist: pulumi<4.0.0,>=3.0.0
Requires-Dist: semver>=2.8.1
Requires-Dist: typing-extensions<5,>=4.11; python_version < "3.11"
Dynamic: description
Dynamic: description-content-type
Dynamic: home-page
Dynamic: keywords
Dynamic: license
Dynamic: project-url
Dynamic: requires-dist
Dynamic: requires-python
Dynamic: summary
